madforhooks/__init__.py
madforhooks/check_execution_order.py
madforhooks/check_test_naming.py
madforhooks/conda_env_sorter.py
madforhooks/no_print_statements.py
madforhooks-0.4.1.dist-info/LICENSE
madforhooks-0.4.1.dist-info/METADATA
madforhooks-0.4.1.dist-info/WHEEL
madforhooks-0.4.1.dist-info/entry_points.txt
madforhooks-0.4.1.dist-info/top_level.txt
madforhooks-0.4.1.dist-info/RECORD
