Metadata-Version: 2.1
Name: madforhooks
Version: 0.4.1
Summary: Random assorted pre-commit hooks
Home-page: https://github.com/MarcoGorelli/madforhooks
Author: Marco Gorelli
License: MIT
Project-URL: Source, https://github.com/MarcoGorelli/madforhooks
Project-URL: Tracker, https://github.com/MarcoGorelli/madforhooks/issues
Keywords: conda,pre-commit
Classifier: Environment :: Console
Classifier: Intended Audience :: Developers
Classifier: License :: OSI Approved :: MIT License
Classifier: Natural Language :: English
Classifier: Operating System :: OS Independent
Classifier: Programming Language :: Python :: 3
Classifier: Programming Language :: Python :: 3 :: Only
Classifier: Topic :: Software Development :: Quality Assurance
Requires-Python: >=3.7.0
License-File: LICENSE
Requires-Dist: GitPython
Requires-Dist: ruamel.yaml (>=0.15)
